r00android_patch/__init__.py
r00android_patch/dbpatch.py
r00android_patch/efs/__init__.py
r00android_patch/efs/manager_efs.py
r00android_patch/kernel/__init__.py
r00android_patch/prop/__init__.py
r00android_patch/prop/manager_prop.py
r00android_patch-0.1.0.dist-info/METADATA
r00android_patch-0.1.0.dist-info/WHEEL
r00android_patch-0.1.0.dist-info/RECORD
