Metadata-Version: 2.4
Name: r00android_patch
Version: 0.1.0
Requires-Python: >=3.12
Requires-Dist: r00android-fake
Requires-Dist: r00arango-connector
Requires-Dist: r00textutil
